{
    "key": "group_595cdd08d299b",
    "title": "Gestione calendario e biglietti on-line",
    "fields": [
        {
            "key": "field_595cdd21be326",
            "label": "CTA Calendario",
            "name": "cta_calendario",
            "type": "text",
            "instructions": "",
            "required": 0,
            "conditional_logic": 0,
            "wrapper": {
                "width": "",
                "class": "",
                "id": ""
            },
            "default_value": "",
            "placeholder": "",
            "prepend": "",
            "append": "",
            "maxlength": ""
        },
        {
            "key": "field_595cdd35be327",
            "label": "URL Calendario",
            "name": "url_calendario",
            "type": "text",
            "instructions": "",
            "required": 0,
            "conditional_logic": 0,
            "wrapper": {
                "width": "",
                "class": "",
                "id": ""
            },
            "default_value": "",
            "placeholder": "",
            "prepend": "",
            "append": "",
            "maxlength": ""
        },
        {
            "key": "field_595cdd40be328",
            "label": "CTA Biglietti on-line",
            "name": "cta_biglietti_online",
            "type": "text",
            "instructions": "",
            "required": 0,
            "conditional_logic": 0,
            "wrapper": {
                "width": "",
                "class": "",
                "id": ""
            },
            "default_value": "",
            "placeholder": "",
            "prepend": "",
            "append": "",
            "maxlength": ""
        },
        {
            "key": "field_595cdd53be329",
            "label": "Link Biglietti on-line",
            "name": "link_biglietti_online",
            "type": "text",
            "instructions": "",
            "required": 0,
            "conditional_logic": 0,
            "wrapper": {
                "width": "",
                "class": "",
                "id": ""
            },
            "default_value": "",
            "placeholder": "",
            "prepend": "",
            "append": "",
            "maxlength": ""
        },
        {
            "key": "field_595cdeb4c913c",
            "label": "CTA Newsletter",
            "name": "cta_newsletter",
            "type": "text",
            "instructions": "",
            "required": 0,
            "conditional_logic": 0,
            "wrapper": {
                "width": "",
                "class": "",
                "id": ""
            },
            "default_value": "",
            "placeholder": "",
            "prepend": "",
            "append": "",
            "maxlength": ""
        },
        {
            "key": "field_595cdebdc913d",
            "label": "Link Newsletter",
            "name": "link_newsletter",
            "type": "text",
            "instructions": "",
            "required": 0,
            "conditional_logic": 0,
            "wrapper": {
                "width": "",
                "class": "",
                "id": ""
            },
            "default_value": "",
            "placeholder": "",
            "prepend": "",
            "append": "",
            "maxlength": ""
        },
        {
            "key": "field_59bfba19e0e13",
            "label": "Numero di telefono per bottone mobile",
            "name": "numero_telefono_diretto",
            "type": "number",
            "instructions": "",
            "required": 0,
            "conditional_logic": 0,
            "wrapper": {
                "width": "",
                "class": "",
                "id": ""
            },
            "default_value": "",
            "placeholder": "",
            "prepend": "",
            "append": "",
            "min": "",
            "max": "",
            "step": ""
        },
        {
            "key": "field_5b2b8b42633f5",
            "label": "Mostrare calendario in homepage?",
            "name": "home_calendar_show",
            "type": "select",
            "instructions": "",
            "required": 0,
            "conditional_logic": 0,
            "wrapper": {
                "width": "",
                "class": "",
                "id": ""
            },
            "choices": {
                "si": "Sì",
                "no": "No"
            },
            "default_value": [],
            "allow_null": 0,
            "multiple": 0,
            "ui": 0,
            "ajax": 0,
            "return_format": "value",
            "placeholder": ""
        },
        {
            "key": "field_5b2b8b67633f6",
            "label": "URL API calendario",
            "name": "calendar_api_url",
            "type": "text",
            "instructions": "es.: https:\/\/www.teatrofrancoparenti.it\/app\/wp-admin\/",
            "required": 1,
            "conditional_logic": 0,
            "wrapper": {
                "width": "",
                "class": "",
                "id": ""
            },
            "default_value": "",
            "placeholder": "",
            "prepend": "",
            "append": "",
            "maxlength": ""
        },
        {
            "key": "field_5de8f8d30db47",
            "label": "URL carrello SRO",
            "name": "carrello_sro",
            "type": "url",
            "instructions": "",
            "required": 0,
            "conditional_logic": 0,
            "wrapper": {
                "width": "",
                "class": "",
                "id": ""
            },
            "default_value": "",
            "placeholder": ""
        },
        {
            "key": "field_5f97f3db907c9",
            "label": "Messaggio pagina Cartellone e Calendario",
            "name": "messaggio_pagina_cartellone_e_calendario",
            "type": "textarea",
            "instructions": "",
            "required": 0,
            "conditional_logic": 0,
            "wrapper": {
                "width": "",
                "class": "",
                "id": ""
            },
            "default_value": "",
            "placeholder": "",
            "maxlength": "",
            "rows": "",
            "new_lines": "br"
        },
        {
            "key": "field_61014ab59cfe3",
            "label": "Avviso modal",
            "name": "avviso_spettacolo_overlay_globale",
            "type": "textarea",
            "instructions": "Questo avviso comparirà nelle modal di tutti gli spettacoli.",
            "required": 0,
            "conditional_logic": 0,
            "wrapper": {
                "width": "",
                "class": "",
                "id": ""
            },
            "default_value": "",
            "placeholder": "",
            "maxlength": "",
            "rows": "",
            "new_lines": "br"
        },
        {
            "key": "field_60dee9968bf01",
            "label": "CTA Cartellone Home (solo mobile)",
            "name": "cta_cartellone_home_solo_mobile",
            "type": "text",
            "instructions": "",
            "required": 0,
            "conditional_logic": 0,
            "wrapper": {
                "width": "",
                "class": "",
                "id": ""
            },
            "default_value": "",
            "placeholder": "",
            "prepend": "",
            "append": "",
            "maxlength": ""
        },
        {
            "key": "field_60dee9f08bf02",
            "label": "URL Cartellone",
            "name": "url_cartellone",
            "type": "text",
            "instructions": "",
            "required": 1,
            "conditional_logic": 0,
            "wrapper": {
                "width": "",
                "class": "",
                "id": ""
            },
            "default_value": "",
            "placeholder": "",
            "prepend": "",
            "append": "",
            "maxlength": ""
        },
        {
            "key": "field_60f15d7423428",
            "label": "Attivare le chiamate a ESRO nella pagina Cartellone?",
            "name": "disattivare_chiamate_esro_pagina_cartellone",
            "type": "true_false",
            "instructions": "",
            "required": 0,
            "conditional_logic": 0,
            "wrapper": {
                "width": "",
                "class": "",
                "id": ""
            },
            "message": "",
            "default_value": 0,
            "ui": 1,
            "ui_on_text": "",
            "ui_off_text": ""
        }
    ],
    "location": [
        [
            {
                "param": "options_page",
                "operator": "==",
                "value": "acf-options-calendario-e-biglietti-on-line"
            }
        ]
    ],
    "menu_order": 0,
    "position": "normal",
    "style": "default",
    "label_placement": "top",
    "instruction_placement": "label",
    "hide_on_screen": "",
    "active": true,
    "description": "",
    "modified": 1627474655
}